sql_logger
