Metadata-Version: 2.1
Name: sql-logger
Version: 0.0.2
Summary: Log to an SQL database from multiple threads.
Home-page: https://github.com/robotpt/sql-logger
Author: Adam Hamden
Author-email: ahamden@usc.edu
License: MIT
Platform: UNKNOWN
Classifier: License :: OSI Approved :: MIT License
Classifier: Programming Language :: Python
Classifier: Programming Language :: Python :: 3
Classifier: Programming Language :: Python :: 3.6
Classifier: Programming Language :: Python :: Implementation :: CPython
Classifier: Programming Language :: Python :: Implementation :: PyPy
Requires-Python: >=3.6.0
